vectorizedb/__init__.py
vectorizedb-0.9.0.dist-info/LICENSE
vectorizedb-0.9.0.dist-info/METADATA
vectorizedb-0.9.0.dist-info/WHEEL
vectorizedb-0.9.0.dist-info/RECORD
