Metadata-Version: 2.1
Name: vectorizedb
Version: 0.9.0
Summary: VectorizeDB is a database for vectorized data and metadata, allowing for fast similarity search and retrieval.
Home-page: https://github.com/aion-labs/vectorizedb
License: Apache
Author: JJ Ben-Joseph
Author-email: jj@tensorspace.ai
Requires-Python: >3.9
Classifier: Development Status :: 3 - Alpha
Classifier: Intended Audience :: Developers
Classifier: Intended Audience :: Science/Research
Classifier: License :: OSI Approved :: Apache Software License
Classifier: License :: Other/Proprietary License
Classifier: Operating System :: OS Independent
Classifier: Programming Language :: Python :: 3
Classifier: Programming Language :: Python :: 3.10
Classifier: Programming Language :: Python :: 3.11
Classifier: Programming Language :: Python :: 3.12
Classifier: Programming Language :: Python :: 3 :: Only
Classifier: Programming Language :: Python :: 3.9
Classifier: Topic :: Database
Classifier: Topic :: Scientific/Engineering :: Information Analysis
Requires-Dist: hnswlib
Requires-Dist: lmdb
Requires-Dist: msgpack
Requires-Dist: numpy
